gbdmigration/__init__.py
gbdmigration/applier.py
gbdmigration/applyer.py
gbdmigration/done.py
gbdmigration/done_files_migration.json
gbdmigration/download.py
gbdmigration/entities.py
gbdmigration/error_handler.py
gbdmigration/execs.py
gbdmigration/filescanner.py
gbdmigration/localdb.py
gbdmigration/organiser.py
gbdmigration/pipelines.py
gbdmigration/secrets.txt
gbdmigration/upload.py
gbdmigration/utilities.py
gbdmigration/wrappers.py
gbdmigration-1.0.24.dist-info/METADATA
gbdmigration-1.0.24.dist-info/WHEEL
gbdmigration-1.0.24.dist-info/entry_points.txt
gbdmigration-1.0.24.dist-info/top_level.txt
gbdmigration-1.0.24.dist-info/RECORD
